README.md
flask_jsglue.py
setup.py
Flask_JSGlue2.egg-info/PKG-INFO
Flask_JSGlue2.egg-info/SOURCES.txt
Flask_JSGlue2.egg-info/dependency_links.txt
Flask_JSGlue2.egg-info/not-zip-safe
Flask_JSGlue2.egg-info/requires.txt
Flask_JSGlue2.egg-info/top_level.txt