Metadata-Version: 1.1
Name: Flask-JSGlue2
Version: 0.3.3
Summary: Flask-JSGlue helps hook up your Flask application nicely with the front end.
Home-page: http://stewartpark.github.com/Flask-JSGlue
Author: Stewart Park
Author-email: stewartpark92@gmail.com
License: BSD
Platform: any
Classifier: Environment :: Web Environment
Classifier: Intended Audience :: Developers
Classifier: License :: OSI Approved :: BSD License
Classifier: Operating System :: OS Independent
Classifier: Programming Language :: Python
Classifier: Topic :: Internet :: WWW/HTTP :: Dynamic Content
Classifier: Topic :: Software Development :: Libraries :: Python Modules
